dranspose/__init__.py
dranspose/cli.py
dranspose/controller.py
dranspose/debug_worker.py
dranspose/distributed.py
dranspose/event.py
dranspose/ingester.py
dranspose/mapping.py
dranspose/parameters.py
dranspose/protocol.py
dranspose/reducer.py
dranspose/replay.py
dranspose/worker.py
dranspose/workload_generator.py
dranspose/data/__init__.py
dranspose/data/albaem.py
dranspose/data/contrast.py
dranspose/data/eiger_legacy.py
dranspose/data/lecroy.py
dranspose/data/pcap.py
dranspose/data/positioncap.py
dranspose/data/sardana.py
dranspose/data/stream1.py
dranspose/data/xspress3.py
dranspose/frontend/index.html
dranspose/helpers/__init__.py
dranspose/helpers/h5dict.py
dranspose/helpers/h5types.py
dranspose/helpers/jsonpath_slice_ext.py
dranspose/helpers/utils.py
dranspose/ingesters/__init__.py
dranspose/ingesters/http_sardana.py
dranspose/ingesters/tcp_positioncap.py
dranspose/ingesters/zmqpull_eiger_legacy.py
dranspose/ingesters/zmqpull_single.py
dranspose/ingesters/zmqsub_albaem.py
dranspose/ingesters/zmqsub_contrast.py
dranspose/ingesters/zmqsub_lecroy.py
dranspose/ingesters/zmqsub_pcap.py
dranspose/ingesters/zmqsub_xspress3.py
dranspose/middlewares/__init__.py
dranspose/middlewares/contrast.py
dranspose/middlewares/eiger_legacy.py
dranspose/middlewares/lecroy.py
dranspose/middlewares/pcap.py
dranspose/middlewares/positioncap.py
dranspose/middlewares/sardana.py
dranspose/middlewares/stream1.py
dranspose/middlewares/xspress.py
dranspose-0.1.1.dist-info/licenses/LICENSE
dranspose-0.1.1.dist-info/METADATA
dranspose-0.1.1.dist-info/WHEEL
dranspose-0.1.1.dist-info/entry_points.txt
dranspose-0.1.1.dist-info/top_level.txt
dranspose-0.1.1.dist-info/RECORD
