Metadata-Version: 2.4
Name: dranspose
Version: 0.1.1
Summary: A stream matrix transposition framework
Author-email: Felix Engelmann <felix-github@nlogn.org>
License-Expression: MIT
Project-URL: Homepage, https://github.com/felix-engelmann/dranspose
Project-URL: Bug Tracker, https://github.com/felix-engelmann/dranspose/issues
Classifier: Programming Language :: Python :: 3
Classifier: Operating System :: OS Independent
Requires-Python: >=3.10
License-File: LICENSE
Requires-Dist: pyzmq
Requires-Dist: redis[hiredis]
Requires-Dist: fastapi
Requires-Dist: uvicorn
Requires-Dist: numpy
Requires-Dist: pydantic
Requires-Dist: pydantic-settings
Requires-Dist: jsonpath-ng
Requires-Dist: cbor2
Requires-Dist: redis-logs
Provides-Extra: tests
Requires-Dist: pytest; extra == "tests"
Requires-Dist: pytest-asyncio; extra == "tests"
Requires-Dist: aiohttp; extra == "tests"
Requires-Dist: psutil; extra == "tests"
Requires-Dist: types-psutil; extra == "tests"
Requires-Dist: pytest-plt; extra == "tests"
Requires-Dist: h5pyd; extra == "tests"
Provides-Extra: docs
Requires-Dist: mkdocs; extra == "docs"
Requires-Dist: mkdocstrings[python]; extra == "docs"
Requires-Dist: mkdocs-material; extra == "docs"
Provides-Extra: bench
Requires-Dist: psutil; extra == "bench"
Requires-Dist: types-psutil; extra == "bench"
Dynamic: license-file
